trackopy/trackobot.py
trackopy/__init__.py
trackopy/scripts/__init__.py
trackopy/scripts/tb.py
tests/__init__.py
tests/test_trackobot.py
trackopy-2.0.2.dist-info/DESCRIPTION.rst
trackopy-2.0.2.dist-info/top_level.txt
trackopy-2.0.2.dist-info/RECORD
trackopy-2.0.2.dist-info/metadata.json
trackopy-2.0.2.dist-info/METADATA
trackopy-2.0.2.dist-info/WHEEL
trackopy-2.0.2.dist-info/entry_points.txt
