Metadata-Version: 2.0
Name: trackopy
Version: 2.0.2
Summary: Python wrapper for the Trackobot API
Home-page: https://github.com/ThaWeatherman/trackopy
Author: Sean Beck
Author-email: seanmckaybeck@gmail.com
License: MIT
Keywords: trackobot hearthstone
Platform: any
Classifier: Environment :: Web Environment
Classifier: Intended Audience :: Developers
Classifier: License :: OSI Approved :: MIT License
Classifier: Operating System :: OS Independent
Classifier: Programming Language :: Python
Classifier: Topic :: Internet :: WWW/HTTP :: Dynamic Content
Classifier: Topic :: Software Development :: Libraries :: Python Modules
Classifier: Programming Language :: Python :: 3
Requires-Dist: requests
Requires-Dist: click
